{
  "id": 1757,
  "created_at": "2025-02-18T05:36:06.944061+00:00",
  "name": "3D tramflow",
  "description": "click to paint \nthen move the slider to other side \nthen paint again \nthen move the slider to other side, \nslider switches between 3Ddivergence and 3Dcurl",
  "body": {
    "uniforms": [
      {
        "name": "a",
        "value": 0,
        "minRange": 0,
        "maxRange": 1
      }
    ],
    "textures": [
      {
        "img": "/textures/blank.png"
      },
      {
        "img": "/textures/blank.png"
      }
    ],
    "float32Enabled": false
  },
  "visibility": "public",
  "profile": {
    "username": "lomateron"
  }
}